axp/__init__.py
axp-0.0.1.dist-info/METADATA
axp-0.0.1.dist-info/WHEEL
axp-0.0.1.dist-info/RECORD
