Metadata-Version: 2.4
Name: axp
Version: 0.0.1
Summary: Agentic experience platform - axp.systems
Project-URL: Homepage, https://axp.systems
Project-URL: Repository, https://github.com/axp-systems/axp
Author-email: "axp.systems" <hello@axp.systems>
License-Expression: MIT
Keywords: agentic,agents,ai,llm
Classifier: Development Status :: 1 - Planning
Classifier: Intended Audience :: Developers
Classifier: License :: OSI Approved :: MIT License
Classifier: Programming Language :: Python :: 3
